f4fscript/__init__.py
f4fscript/f4fscript.py
f4fscript-2.0.dist-info/LICENSE
f4fscript-2.0.dist-info/METADATA
f4fscript-2.0.dist-info/WHEEL
f4fscript-2.0.dist-info/top_level.txt
f4fscript-2.0.dist-info/RECORD
