Metadata-Version: 2.1
Name: f4fscript
Version: 2.0
Summary: A follow for follow script for instagram.
Home-page: https://github.com/pypa/sampleproject
Author: NamastexBeast
Author-email: Abhinav.bhardwaj.56624@gmail.com
Project-URL: Bug Tracker, https://github.com/pypa/sampleproject/issues
Classifier: Programming Language :: Python :: 3
Classifier: License :: OSI Approved :: MIT License
Classifier: Operating System :: OS Independent
Requires-Python: >=3.6
License-File: LICENSE
